[
{"alpha1_interaction_http://www.imgt.org/3Dstructure-DB/cgi/details.cgi?pdbcode=3OXR&Part=CONT_DETAILS&domcontcode=3OXRDC000": {"1": [5, 7, 33, 59, 63, 66, 7, 9, 45, 63, 66, 67, 70, 9, 66, 70], "2": [7, 9, 45, 63, 66, 67, 70, 9, 66, 70, 66, 70], "3": [9, 66, 70, 66, 70, 66, 69, 70, 73], "4": [66, 70, 66, 69, 70, 73, 70], "5": [66, 69, 70, 73, 70, 9, 70, 73], "6": [70, 9, 70, 73, 73, 77], "7": [9, 70, 73, 73, 77, 73, 76, 77], "8": [73, 77, 73, 76, 77, 77, 80, 81, 84]}},
{"alpha2_interaction_http://www.imgt.org/3Dstructure-DB/cgi/details.cgi?pdbcode=3OXR&Part=CONT_DETAILS&domcontcode=3OXRDC001": {"1": [70, 73, 77, 81, 9, 70, 9, 70], "2": [9, 70, 9, 70], "3": [9, 70], "4": [63, 66, 67, 70], "5": [63, 66, 67, 70, 7, 9, 24, 67], "6": [63, 66, 67, 70, 7, 9, 24, 67, 7, 59, 63], "7": [7, 9, 24, 67, 7, 59, 63, 58, 59], "8": [7, 59, 63, 58, 59, 26, 33, 54, 55, 58, 59]}}
]